caprover_api_toolkit/__init__.py
caprover_api_toolkit/caprover_api_toolkit.py
caprover_api_toolkit-0.2.6.dist-info/AUTHORS.rst
caprover_api_toolkit-0.2.6.dist-info/LICENSE
caprover_api_toolkit-0.2.6.dist-info/METADATA
caprover_api_toolkit-0.2.6.dist-info/WHEEL
caprover_api_toolkit-0.2.6.dist-info/top_level.txt
caprover_api_toolkit-0.2.6.dist-info/RECORD
