Metadata-Version: 2.1
Name: caprover-api-toolkit
Version: 0.2.6
Summary: unofficial caprover api to deploy apps to caprover
Home-page: https://github.com/neo3k/caprover-api-toolkit
Author: Boris Vera
Author-email: boris@wearevera.com
License: MIT license
Keywords: caprover_api_toolkit
Classifier: Development Status :: 2 - Pre-Alpha
Classifier: Intended Audience :: Developers
Classifier: License :: OSI Approved :: MIT License
Classifier: Natural Language :: English
Classifier: Programming Language :: Python :: 3
Classifier: Programming Language :: Python :: 3.6
Classifier: Programming Language :: Python :: 3.7
Classifier: Programming Language :: Python :: 3.8
Requires-Python: >=3.6
License-File: LICENSE
License-File: AUTHORS.rst
Requires-Dist: requests (>=2.25.1)
Requires-Dist: PyYAML (>=5.4.1)
Requires-Dist: infisical (>=1.5.0)
